simplex/__init__.py
simplex/browserActor.py
simplex/enums.py
simplex/prompts.py
simplex/simplex.py
simplex/utils.py
simplex_labs-0.1.0.dist-info/LICENSE
simplex_labs-0.1.0.dist-info/METADATA
simplex_labs-0.1.0.dist-info/WHEEL
simplex_labs-0.1.0.dist-info/entry_points.txt
simplex_labs-0.1.0.dist-info/top_level.txt
simplex_labs-0.1.0.dist-info/RECORD
